{"adj_List": "{1: [2, 5, 4], 2: [2, 3, 4], 3: [4, 1, 5, 2], 4: [4, 1, 5, 3], 5: [3, 1, 4, 2, 5]}", "end_states": "{1: 'end_state', 2: 'end_state', 3: 'not_end_state', 4: 'not_end_state', 5: 'not_end_state'}", "nodes": "[1, 2, 3, 4, 5]", "edges": "[(1, 2, 'f'), (1, 2, 'g'), (1, 2, 'v'), (1, 5, 'i'), (1, 5, 't'), (1, 5, 'u'), (1, 4, 'r'), (2, 2, 'f'), (2, 2, 'g'), (2, 2, 't'), (2, 3, 'i'), (2, 3, 'y'), (2, 4, 'r'), (3, 4, 'g'), (3, 1, 'i'), (3, 1, 'r'), (3, 5, 'u'), (3, 2, 'y'), (4, 4, 'g'), (4, 4, 'r'), (4, 1, 'i'), (4, 1, 't'), (4, 5, 'v'), (4, 3, 'y'), (5, 3, 'f'), (5, 3, 't'), (5, 1, 'g'), (5, 1, 'i'), (5, 4, 'u'), (5, 2, 'v'), (5, 5, 'y')]", "imgFP": "./InfDFA/Final_Transition_Structure_5_8_11.png", "isInfinite": "True"}